Workbook

Sheet Инвентаризация
A1: Дата добавления | B1: Бренд | C1: Артикул | D1: Наименование | E1: Количество | F1: Закупочная цена, ₸ | G1: Продажная цена, ₸ | H1: Папка | I1: Фото | J1: Ссылки | K1: Карточка | L1: GitHub | M1: Kaspi | N1: Kaspi Код Товара | O1: Место хранения | P1: Поставщик | Q1: Дата обновления | R1: Примечание
A2: 46235 | B2: Brembo | C2: P85083 | D2: Колодки тормозные задние | E2: 1 | F2: 0 | G2: 14000 | H2: Да | I2: Да | J2: Да | K2: Да | L2: Да | M2: Да | N2: 172835238 | P2: Leopart | Q2: 46236 | R2: Первая карточка проекта
A3: 46236 | B3: MK KASHIYAMA | C3: D3132H | D3: Колодки тормозные задние | E3: 1 | F3: 0 | G3: 8000 | H3: Да | I3: Да | J3: Да | K3: Да | L3: Да | M3: Да | N3: 172843950 | P3: ARMTEK | Q3: 46236 | R3: Эталонная карточка v1.2
A4: 46237 | B4: MK KASHIYAMA | C4: D11173MH | D4: Колодки тормозные передние | E4: 2 | F4: 0 | G4: 12000 | H4: Да | I4: Да | J4: Да | K4: Да | L4: Да | M4: Да | N4: 172870174 | Q4: 46237
A5: 46237 | B5: MK KASHIYAMA | C5: D1231MH | D5: Колодки тормозные передние | E5: 1 | F5: 0 | G5: 12000 | H5: Да | I5: Да | J5: Да | K5: Да | L5: Да | M5: Да | N5: 172879327 | P5: ARMTEK | Q5: 46237
A6: 46237 | B6: MK KASHIYAMA | C6: D11115MH | D6: Колодки тормозные передние | E6: 1 | F6: 0 | G6: 11000 | H6: Да | I6: Да | J6: Да | K6: Да | L6: Да | M6: Да | N6: 172886515 | Q6: 46237
A7: 46237 | B7: MK KASHIYAMA | C7: D6108H | D7: Колодки тормозные передние | E7: 1 | F7: 0 | G7: 6000 | H7: Да | I7: Да | J7: Да | K7: Да | L7: Да | M7: Да | N7: 172903965 | P7: ARMTEK | Q7: 46237
A8: 46238 | B8: MK KASHIYAMA | C8: D2082MH | D8: Колодки тормозные передние | E8: 1 | F8: 0 | G8: 10000 | H8: Да | I8: Да | J8: Да | K8: Да | L8: Да | M8: Да | N8: 172985889 | Q8: 46238
A9: 46239 | B9: MK KASHIYAMA | C9: K2333 | D9: Колодки тормозные задние барабанные, комплект | E9: 1 | F9: 0 | G9: 12000 | H9: Да | I9: Да | J9: Да | K9: Да | L9: Да | M9: Да | N9: 172999972 | Q9: 46239

Sheet Склад
A1: Бренд | B1: Артикул | C1: Наименование | D1: Количество | E1: Закупочная цена, ₸ | F1: Продажная цена, ₸ | G1: Прибыль с единицы, ₸ | H1: Маржа, % | I1: Стоимость остатка, ₸ | J1: Потенциальная выручка, ₸ | K1: Потенциальная прибыль, ₸ | L1: Kaspi | M1: Kaspi SKU | N1: Место хранения | O1: Поставщик | P1: Дата обновления
A2: =IF(Инвентаризация!C2="","",Инвентаризация!B2) -> Brembo | B2: =IF(Инвентаризация!C2="","",Инвентаризация!C2) -> P85083 | C2: =IF(Инвентаризация!C2="","",Инвентаризация!D2) -> Колодки тормозные задние | D2: =IF(Инвентаризация!C2="","",Инвентаризация!E2) -> 1 | E2: =IF(Инвентаризация!C2="","",Инвентаризация!F2) -> 0 | F2: =IF(Инвентаризация!C2="","",Инвентаризация!G2) -> 14000 | G2: =IF(OR(E2="",F2=""),"",F2-E2) -> 14000 | H2: =IFERROR(G2/F2,"") -> 1 | I2: =IF(OR(D2="",E2=""),"",D2*E2) -> 0 | J2: =IF(OR(D2="",F2=""),"",D2*F2) -> 14000 | K2: =IF(OR(D2="",G2=""),"",D2*G2) -> 14000 | L2: =IF(Инвентаризация!C2="","",Инвентаризация!M2) -> Да | M2: =IF(Инвентаризация!C2="","",Инвентаризация!N2) -> 172835238 | N2: =IF(Инвентаризация!C2="","",Инвентаризация!O2) -> 0 | O2: =IF(Инвентаризация!C2="","",Инвентаризация!P2) -> Leopart | P2: =IF(Инвентаризация!C2="","",Инвентаризация!Q2) -> 46236
A3: =IF(Инвентаризация!C3="","",Инвентаризация!B3) -> MK KASHIYAMA | B3: =IF(Инвентаризация!C3="","",Инвентаризация!C3) -> D3132H | C3: =IF(Инвентаризация!C3="","",Инвентаризация!D3) -> Колодки тормозные задние | D3: =IF(Инвентаризация!C3="","",Инвентаризация!E3) -> 1 | E3: =IF(Инвентаризация!C3="","",Инвентаризация!F3) -> 0 | F3: =IF(Инвентаризация!C3="","",Инвентаризация!G3) -> 8000 | G3: =IF(OR(E3="",F3=""),"",F3-E3) -> 8000 | H3: =IFERROR(G3/F3,"") -> 1 | I3: =IF(OR(D3="",E3=""),"",D3*E3) -> 0 | J3: =IF(OR(D3="",F3=""),"",D3*F3) -> 8000 | K3: =IF(OR(D3="",G3=""),"",D3*G3) -> 8000 | L3: =IF(Инвентаризация!C3="","",Инвентаризация!M3) -> Да | M3: =IF(Инвентаризация!C3="","",Инвентаризация!N3) -> 172843950 | N3: =IF(Инвентаризация!C3="","",Инвентаризация!O3) -> 0 | O3: =IF(Инвентаризация!C3="","",Инвентаризация!P3) -> ARMTEK | P3: =IF(Инвентаризация!C3="","",Инвентаризация!Q3) -> 46236
A4: =IF(Инвентаризация!C4="","",Инвентаризация!B4) -> MK KASHIYAMA | B4: =IF(Инвентаризация!C4="","",Инвентаризация!C4) -> D11173MH | C4: =IF(Инвентаризация!C4="","",Инвентаризация!D4) -> Колодки тормозные передние | D4: =IF(Инвентаризация!C4="","",Инвентаризация!E4) -> 2 | E4: =IF(Инвентаризация!C4="","",Инвентаризация!F4) -> 0 | F4: =IF(Инвентаризация!C4="","",Инвентаризация!G4) -> 12000 | G4: =IF(OR(E4="",F4=""),"",F4-E4) -> 12000 | H4: =IFERROR(G4/F4,"") -> 1 | I4: =IF(OR(D4="",E4=""),"",D4*E4) -> 0 | J4: =IF(OR(D4="",F4=""),"",D4*F4) -> 24000 | K4: =IF(OR(D4="",G4=""),"",D4*G4) -> 24000 | L4: =IF(Инвентаризация!C4="","",Инвентаризация!M4) -> Да | M4: =IF(Инвентаризация!C4="","",Инвентаризация!N4) -> 172870174 | N4: =IF(Инвентаризация!C4="","",Инвентаризация!O4) -> 0 | O4: =IF(Инвентаризация!C4="","",Инвентаризация!P4) -> 0 | P4: =IF(Инвентаризация!C4="","",Инвентаризация!Q4) -> 46237
A5: =IF(Инвентаризация!C5="","",Инвентаризация!B5) -> MK KASHIYAMA | B5: =IF(Инвентаризация!C5="","",Инвентаризация!C5) -> D1231MH | C5: =IF(Инвентаризация!C5="","",Инвентаризация!D5) -> Колодки тормозные передние | D5: =IF(Инвентаризация!C5="","",Инвентаризация!E5) -> 1 | E5: =IF(Инвентаризация!C5="","",Инвентаризация!F5) -> 0 | F5: =IF(Инвентаризация!C5="","",Инвентаризация!G5) -> 12000 | G5: =IF(OR(E5="",F5=""),"",F5-E5) -> 12000 | H5: =IFERROR(G5/F5,"") -> 1 | I5: =IF(OR(D5="",E5=""),"",D5*E5) -> 0 | J5: =IF(OR(D5="",F5=""),"",D5*F5) -> 12000 | K5: =IF(OR(D5="",G5=""),"",D5*G5) -> 12000 | L5: =IF(Инвентаризация!C5="","",Инвентаризация!M5) -> Да | M5: =IF(Инвентаризация!C5="","",Инвентаризация!N5) -> 172879327 | N5: =IF(Инвентаризация!C5="","",Инвентаризация!O5) -> 0 | O5: =IF(Инвентаризация!C5="","",Инвентаризация!P5) -> ARMTEK | P5: =IF(Инвентаризация!C5="","",Инвентаризация!Q5) -> 46237
A6: =IF(Инвентаризация!C6="","",Инвентаризация!B6) -> MK KASHIYAMA | B6: =IF(Инвентаризация!C6="","",Инвентаризация!C6) -> D11115MH | C6: =IF(Инвентаризация!C6="","",Инвентаризация!D6) -> Колодки тормозные передние | D6: =IF(Инвентаризация!C6="","",Инвентаризация!E6) -> 1 | E6: =IF(Инвентаризация!C6="","",Инвентаризация!F6) -> 0 | F6: =IF(Инвентаризация!C6="","",Инвентаризация!G6) -> 11000 | G6: =IF(OR(E6="",F6=""),"",F6-E6) -> 11000 | H6: =IFERROR(G6/F6,"") -> 1 | I6: =IF(OR(D6="",E6=""),"",D6*E6) -> 0 | J6: =IF(OR(D6="",F6=""),"",D6*F6) -> 11000 | K6: =IF(OR(D6="",G6=""),"",D6*G6) -> 11000 | L6: =IF(Инвентаризация!C6="","",Инвентаризация!M6) -> Да | M6: =IF(Инвентаризация!C6="","",Инвентаризация!N6) -> 172886515 | N6: =IF(Инвентаризация!C6="","",Инвентаризация!O6) -> 0 | O6: =IF(Инвентаризация!C6="","",Инвентаризация!P6) -> 0 | P6: =IF(Инвентаризация!C6="","",Инвентаризация!Q6) -> 46237
A7: =IF(Инвентаризация!C7="","",Инвентаризация!B7) -> MK KASHIYAMA | B7: =IF(Инвентаризация!C7="","",Инвентаризация!C7) -> D6108H | C7: =IF(Инвентаризация!C7="","",Инвентаризация!D7) -> Колодки тормозные передние | D7: =IF(Инвентаризация!C7="","",Инвентаризация!E7) -> 1 | E7: =IF(Инвентаризация!C7="","",Инвентаризация!F7) -> 0 | F7: =IF(Инвентаризация!C7="","",Инвентаризация!G7) -> 6000 | G7: =IF(OR(E7="",F7=""),"",F7-E7) -> 6000 | H7: =IFERROR(G7/F7,"") -> 1 | I7: =IF(OR(D7="",E7=""),"",D7*E7) -> 0 | J7: =IF(OR(D7="",F7=""),"",D7*F7) -> 6000 | K7: =IF(OR(D7="",G7=""),"",D7*G7) -> 6000 | L7: =IF(Инвентаризация!C7="","",Инвентаризация!M7) -> Да | M7: =IF(Инвентаризация!C7="","",Инвентаризация!N7) -> 172903965 | N7: =IF(Инвентаризация!C7="","",Инвентаризация!O7) -> 0 | O7: =IF(Инвентаризация!C7="","",Инвентаризация!P7) -> ARMTEK | P7: =IF(Инвентаризация!C7="","",Инвентаризация!Q7) -> 46237
A8: =IF(Инвентаризация!C8="","",Инвентаризация!B8) -> MK KASHIYAMA | B8: =IF(Инвентаризация!C8="","",Инвентаризация!C8) -> D2082MH | C8: =IF(Инвентаризация!C8="","",Инвентаризация!D8) -> Колодки тормозные передние | D8: =IF(Инвентаризация!C8="","",Инвентаризация!E8) -> 1 | E8: =IF(Инвентаризация!C8="","",Инвентаризация!F8) -> 0 | F8: =IF(Инвентаризация!C8="","",Инвентаризация!G8) -> 10000 | G8: =IF(OR(E8="",F8=""),"",F8-E8) -> 10000 | H8: =IFERROR(G8/F8,"") -> 1 | I8: =IF(OR(D8="",E8=""),"",D8*E8) -> 0 | J8: =IF(OR(D8="",F8=""),"",D8*F8) -> 10000 | K8: =IF(OR(D8="",G8=""),"",D8*G8) -> 10000 | L8: =IF(Инвентаризация!C8="","",Инвентаризация!M8) -> Да | M8: =IF(Инвентаризация!C8="","",Инвентаризация!N8) -> 172985889 | N8: =IF(Инвентаризация!C8="","",Инвентаризация!O8) -> 0 | O8: =IF(Инвентаризация!C8="","",Инвентаризация!P8) -> 0 | P8: =IF(Инвентаризация!C8="","",Инвентаризация!Q8) -> 46238
A9: =IF(Инвентаризация!C9="","",Инвентаризация!B9) -> MK KASHIYAMA | B9: =IF(Инвентаризация!C9="","",Инвентаризация!C9) -> K2333 | C9: =IF(Инвентаризация!C9="","",Инвентаризация!D9) -> Колодки тормозные задние барабанные, комплект | D9: =IF(Инвентаризация!C9="","",Инвентаризация!E9) -> 1 | E9: =IF(Инвентаризация!C9="","",Инвентаризация!F9) -> 0 | F9: =IF(Инвентаризация!C9="","",Инвентаризация!G9) -> 12000 | G9: =IF(OR(E9="",F9=""),"",F9-E9) -> 12000 | H9: =IFERROR(G9/F9,"") -> 1 | I9: =IF(OR(D9="",E9=""),"",D9*E9) -> 0 | J9: =IF(OR(D9="",F9=""),"",D9*F9) -> 12000 | K9: =IF(OR(D9="",G9=""),"",D9*G9) -> 12000 | L9: =IF(Инвентаризация!C9="","",Инвентаризация!M9) -> Да | M9: =IF(Инвентаризация!C9="","",Инвентаризация!N9) -> 172999972 | N9: =IF(Инвентаризация!C9="","",Инвентаризация!O9) -> 0 | O9: =IF(Инвентаризация!C9="","",Инвентаризация!P9) -> 0 | P9: =IF(Инвентаризация!C9="","",Инвентаризация!Q9) -> 46239
A10: =IF(Инвентаризация!C10="","",Инвентаризация!B10) | B10: =IF(Инвентаризация!C10="","",Инвентаризация!C10) | C10: =IF(Инвентаризация!C10="","",Инвентаризация!D10) | D10: =IF(Инвентаризация!C10="","",Инвентаризация!E10) | E10: =IF(Инвентаризация!C10="","",Инвентаризация!F10) | F10: =IF(Инвентаризация!C10="","",Инвентаризация!G10) | G10: =IF(OR(E10="",F10=""),"",F10-E10) | H10: =IFERROR(G10/F10,"") | I10: =IF(OR(D10="",E10=""),"",D10*E10) | J10: =IF(OR(D10="",F10=""),"",D10*F10) | K10: =IF(OR(D10="",G10=""),"",D10*G10) | L10: =IF(Инвентаризация!C10="","",Инвентаризация!M10) | M10: =IF(Инвентаризация!C10="","",Инвентаризация!N10) | N10: =IF(Инвентаризация!C10="","",Инвентаризация!O10) | O10: =IF(Инвентаризация!C10="","",Инвентаризация!P10) | P10: =IF(Инвентаризация!C10="","",Инвентаризация!Q10)
A11: =IF(Инвентаризация!C11="","",Инвентаризация!B11) | B11: =IF(Инвентаризация!C11="","",Инвентаризация!C11) | C11: =IF(Инвентаризация!C11="","",Инвентаризация!D11) | D11: =IF(Инвентаризация!C11="","",Инвентаризация!E11) | E11: =IF(Инвентаризация!C11="","",Инвентаризация!F11) | F11: =IF(Инвентаризация!C11="","",Инвентаризация!G11) | G11: =IF(OR(E11="",F11=""),"",F11-E11) | H11: =IFERROR(G11/F11,"") | I11: =IF(OR(D11="",E11=""),"",D11*E11) | J11: =IF(OR(D11="",F11=""),"",D11*F11) | K11: =IF(OR(D11="",G11=""),"",D11*G11) | L11: =IF(Инвентаризация!C11="","",Инвентаризация!M11) | M11: =IF(Инвентаризация!C11="","",Инвентаризация!N11) | N11: =IF(Инвентаризация!C11="","",Инвентаризация!O11) | O11: =IF(Инвентаризация!C11="","",Инвентаризация!P11) | P11: =IF(Инвентаризация!C11="","",Инвентаризация!Q11)
A12: =IF(Инвентаризация!C12="","",Инвентаризация!B12) | B12: =IF(Инвентаризация!C12="","",Инвентаризация!C12) | C12: =IF(Инвентаризация!C12="","",Инвентаризация!D12) | D12: =IF(Инвентаризация!C12="","",Инвентаризация!E12) | E12: =IF(Инвентаризация!C12="","",Инвентаризация!F12) | F12: =IF(Инвентаризация!C12="","",Инвентаризация!G12) | G12: =IF(OR(E12="",F12=""),"",F12-E12) | H12: =IFERROR(G12/F12,"") | I12: =IF(OR(D12="",E12=""),"",D12*E12) | J12: =IF(OR(D12="",F12=""),"",D12*F12) | K12: =IF(OR(D12="",G12=""),"",D12*G12) | L12: =IF(Инвентаризация!C12="","",Инвентаризация!M12) | M12: =IF(Инвентаризация!C12="","",Инвентаризация!N12) | N12: =IF(Инвентаризация!C12="","",Инвентаризация!O12) | O12: =IF(Инвентаризация!C12="","",Инвентаризация!P12) | P12: =IF(Инвентаризация!C12="","",Инвентаризация!Q12)
A13: =IF(Инвентаризация!C13="","",Инвентаризация!B13) | B13: =IF(Инвентаризация!C13="","",Инвентаризация!C13) | C13: =IF(Инвентаризация!C13="","",Инвентаризация!D13) | D13: =IF(Инвентаризация!C13="","",Инвентаризация!E13) | E13: =IF(Инвентаризация!C13="","",Инвентаризация!F13) | F13: =IF(Инвентаризация!C13="","",Инвентаризация!G13) | G13: =IF(OR(E13="",F13=""),"",F13-E13) | H13: =IFERROR(G13/F13,"") | I13: =IF(OR(D13="",E13=""),"",D13*E13) | J13: =IF(OR(D13="",F13=""),"",D13*F13) | K13: =IF(OR(D13="",G13=""),"",D13*G13) | L13: =IF(Инвентаризация!C13="","",Инвентаризация!M13) | M13: =IF(Инвентаризация!C13="","",Инвентаризация!N13) | N13: =IF(Инвентаризация!C13="","",Инвентаризация!O13) | O13: =IF(Инвентаризация!C13="","",Инвентаризация!P13) | P13: =IF(Инвентаризация!C13="","",Инвентаризация!Q13)
... A500: =IF(Инвентаризация!C500="","",Инвентаризация!B500) | B500: =IF(Инвентаризация!C500="","",Инвентаризация!C500) | C500: =IF(Инвентаризация!C500="","",Инвентаризация!D500) | D500: =IF(Инвентаризация!C500="","",Инвентаризация!E500) | E500: =IF(Инвентаризация!C500="","",Инвентаризация!F500) | F500: =IF(Инвентаризация!C500="","",Инвентаризация!G500) | G500: =IF(OR(E500="",F500=""),"",F500-E500) | H500: =IFERROR(G500/F500,"") | I500: =IF(OR(D500="",E500=""),"",D500*E500) | J500: =IF(OR(D500="",F500=""),"",D500*F500) | K500: =IF(OR(D500="",G500=""),"",D500*G500) | L500: =IF(Инвентаризация!C500="","",Инвентаризация!M500) | M500: =IF(Инвентаризация!C500="","",Инвентаризация!N500) | N500: =IF(Инвентаризация!C500="","",Инвентаризация!O500) | O500: =IF(Инвентаризация!C500="","",Инвентаризация!P500) | P500: =IF(Инвентаризация!C500="","",Инвентаризация!Q500)

Sheet Сводка
A1: Сводка по складу и каталогу
A3: Показатель | B3: Значение | D3: Контроль | E3: Количество
A4: Количество товарных позиций | B4: =COUNTIF(Инвентаризация!C2:C500,"<>") -> 8 | D4: Нет в наличии | E4: =COUNTIF(Инвентаризация!E2:E500,0) -> 0
A5: Общее количество единиц | B5: =SUM(Инвентаризация!E2:E500) -> 9 | D5: Малый остаток (1–2) | E5: =COUNTIFS(Инвентаризация!E2:E500,">=1",Инвентаризация!E2:E500,"<=2") -> 8
A6: Стоимость остатков | B6: =SUMPRODUCT(Инвентаризация!E2:E500,Инвентаризация!F2:F500) -> 0 | D6: Без карточки | E6: =COUNTIF(Инвентаризация!K2:K500,"Нет") -> 0
A7: Потенциальная выручка | B7: =SUMPRODUCT(Инвентаризация!E2:E500,Инвентаризация!G2:G500) -> 97000 | D7: Не опубликовано в Kaspi | E7: =COUNTIF(Инвентаризация!M2:M500,"Нет") -> 0
A8: Потенциальная прибыль | B8: =B7-B6 -> 97000
A9: Опубликовано в Kaspi | B9: =COUNTIF(Инвентаризация!M2:M500,"Да") -> 8
A11: Этап | B11: Выполнено
A12: Папка | B12: =COUNTIF(Инвентаризация!H2:H500,"Да") -> 8
A13: Фото | B13: =COUNTIF(Инвентаризация!I2:I500,"Да") -> 8
A14: Ссылки | B14: =COUNTIF(Инвентаризация!J2:J500,"Да") -> 8
A15: Карточка | B15: =COUNTIF(Инвентаризация!K2:K500,"Да") -> 8
A16: GitHub | B16: =COUNTIF(Инвентаризация!L2:L500,"Да") -> 8
A17: Kaspi | B17: =COUNTIF(Инвентаризация!M2:M500,"Да") -> 8
